[{"ID":191,"Base":0,"PerLevel":0,"Minimum":0},{"ID":190,"Base":100,"PerLevel":0,"Minimum":100},{"ID":171,"Base":6000,"PerLevel":0,"Minimum":6000},{"ID":170,"Base":8000,"PerLevel":0,"Minimum":8000},{"ID":153,"Base":3400,"PerLevel":0,"Minimum":3400},{"ID":152,"Base":3100,"PerLevel":0,"Minimum":3100},{"ID":151,"Base":2700,"PerLevel":0,"Minimum":2700},{"ID":150,"Base":3800,"PerLevel":0,"Minimum":3800},{"ID":130,"Base":1600,"PerLevel":0,"Minimum":1600},{"ID":110,"Base":750,"PerLevel":0,"Minimum":750},{"ID":91,"Base":2800,"PerLevel":0,"Minimum":2800},{"ID":90,"Base":1700,"PerLevel":0,"Minimum":1700},{"ID":70,"Base":300000,"PerLevel":0,"Minimum":300000},{"ID":50,"Base":1300,"PerLevel":0,"Minimum":1300},{"ID":39,"Base":60000,"PerLevel":-500,"Minimum":30000},{"ID":38,"Base":45000,"PerLevel":-500,"Minimum":15000},{"ID":37,"Base":25000,"PerLevel":-400,"Minimum":10000},{"ID":36,"Base":600,"PerLevel":0,"Minimum":600},{"ID":35,"Base":12500,"PerLevel":-250,"Minimum":5000},{"ID":34,"Base":8000,"PerLevel":-175,"Minimum":4000},{"ID":33,"Base":5125,"PerLevel":-125,"Minimum":3000},{"ID":32,"Base":7000,"PerLevel":0,"Minimum":7000},{"ID":31,"Base":2300,"PerLevel":0,"Minimum":2300},{"ID":30,"Base":4500,"PerLevel":0,"Minimum":4500},{"ID":29,"Base":4700,"PerLevel":0,"Minimum":4700},{"ID":28,"Base":3200,"PerLevel":0,"Minimum":3200},{"ID":27,"Base":4100,"PerLevel":0,"Minimum":4100},{"ID":26,"Base":3700,"PerLevel":0,"Minimum":3700},{"ID":25,"Base":2900,"PerLevel":0,"Minimum":2900},{"ID":24,"Base":2200,"PerLevel":0,"Minimum":2200},{"ID":23,"Base":1800,"PerLevel":0,"Minimum":1800},{"ID":22,"Base":3500,"PerLevel":0,"Minimum":3500},{"ID":21,"Base":2600,"PerLevel":0,"Minimum":2600},{"ID":20,"Base":2500,"PerLevel":0,"Minimum":2500},{"ID":19,"Base":2500,"PerLevel":0,"Minimum":2500},{"ID":18,"Base":-1000000,"PerLevel":0,"Minimum":-1000000},{"ID":16,"Base":1500,"PerLevel":0,"Minimum":1500},{"ID":15,"Base":4000,"PerLevel":0,"Minimum":4000},{"ID":14,"Base":3000,"PerLevel":0,"Minimum":3000},{"ID":13,"Base":30000,"PerLevel":-1000,"Minimum":10000},{"ID":12,"Base":5000,"PerLevel":-100,"Minimum":2500},{"ID":11,"Base":2000,"PerLevel":-100,"Minimum":1000},{"ID":10,"Base":1000,"PerLevel":-100,"Minimum":500},{"ID":9,"Base":30000,"PerLevel":0,"Minimum":30000},{"ID":8,"Base":20000,"PerLevel":0,"Minimum":20000},{"ID":7,"Base":10000,"PerLevel":0,"Minimum":10000},{"ID":6,"Base":5000,"PerLevel":0,"Minimum":5000},{"ID":5,"Base":2000,"PerLevel":0,"Minimum":2000},{"ID":4,"Base":1000,"PerLevel":0,"Minimum":1000},{"ID":3,"Base":500,"PerLevel":0,"Minimum":500},{"ID":2,"Base":250,"PerLevel":0,"Minimum":250},{"ID":1,"Base":0,"PerLevel":0,"Minimum":0}]