[{"ID":61,"Name_enUS":"Frost","Name_enGB":"","Name_koKR":"","Name_frFR":"","Name_deDE":"","Name_enCN":"","Name_zhCN":"","Name_enTW":"","Name_Mask":4128894,"SpellIconID":56,"RaceMask":511,"ClassMask":128,"OrderIndex":2,"BackgroundFile":"MageFrost"},{"ID":362,"Name_enUS":"Survival","Name_enGB":"","Name_koKR":"","Name_frFR":"","Name_deDE":"","Name_enCN":"","Name_zhCN":"","Name_enTW":"","Name_Mask":4128894,"SpellIconID":257,"RaceMask":511,"ClassMask":4,"OrderIndex":2,"BackgroundFile":"HunterSurvival"},{"ID":203,"Name_enUS":"Shadow","Name_enGB":"","Name_koKR":"","Name_frFR":"","Name_deDE":"","Name_enCN":"","Name_zhCN":"","Name_enTW":"","Name_Mask":4128894,"SpellIconID":98,"RaceMask":511,"ClassMask":16,"OrderIndex":2,"BackgroundFile":"PriestShadow"},{"ID":281,"Name_enUS":"Feral Combat","Name_enGB":"","Name_koKR":"","Name_frFR":"","Name_deDE":"","Name_enCN":"","Name_zhCN":"","Name_enTW":"","Name_Mask":4128894,"SpellIconID":201,"RaceMask":511,"ClassMask":1024,"OrderIndex":1,"BackgroundFile":"DruidFeralCombat"},{"ID":303,"Name_enUS":"Demonology","Name_enGB":"","Name_koKR":"","Name_frFR":"","Name_deDE":"","Name_enCN":"","Name_zhCN":"","Name_enTW":"","Name_Mask":4128894,"SpellIconID":692,"RaceMask":511,"ClassMask":256,"OrderIndex":1,"BackgroundFile":"WarlockSummoning"},{"ID":202,"Name_enUS":"Holy","Name_enGB":"","Name_koKR":"","Name_frFR":"","Name_deDE":"","Name_enCN":"","Name_zhCN":"","Name_enTW":"","Name_Mask":4128894,"SpellIconID":79,"RaceMask":511,"ClassMask":16,"OrderIndex":1,"BackgroundFile":"PriestHoly"},{"ID":263,"Name_enUS":"Enhancement","Name_enGB":"","Name_koKR":"","Name_frFR":"","Name_deDE":"","Name_enCN":"","Name_zhCN":"","Name_enTW":"","Name_Mask":4128894,"SpellIconID":312,"RaceMask":511,"ClassMask":64,"OrderIndex":1,"BackgroundFile":"ShamanEnhancement"},{"ID":164,"Name_enUS":"Fury","Name_enGB":"","Name_koKR":"","Name_frFR":"","Name_deDE":"","Name_enCN":"","Name_zhCN":"","Name_enTW":"","Name_Mask":4128894,"SpellIconID":456,"RaceMask":511,"ClassMask":1,"OrderIndex":1,"BackgroundFile":"WarriorFury"},{"ID":361,"Name_enUS":"Beast Mastery","Name_enGB":"","Name_koKR":"","Name_frFR":"","Name_deDE":"","Name_enCN":"","Name_zhCN":"","Name_enTW":"","Name_Mask":4128894,"SpellIconID":255,"RaceMask":511,"ClassMask":4,"OrderIndex":0,"BackgroundFile":"HunterBeastMastery"},{"ID":302,"Name_enUS":"Affliction","Name_enGB":"","Name_koKR":"","Name_frFR":"","Name_deDE":"","Name_enCN":"","Name_zhCN":"","Name_enTW":"","Name_Mask":4128894,"SpellIconID":150,"RaceMask":511,"ClassMask":256,"OrderIndex":0,"BackgroundFile":"WarlockCurses"},{"ID":161,"Name_enUS":"Arms","Name_enGB":"","Name_koKR":"","Name_frFR":"","Name_deDE":"","Name_enCN":"","Name_zhCN":"","Name_enTW":"","Name_Mask":4128894,"SpellIconID":1462,"RaceMask":511,"ClassMask":1,"OrderIndex":0,"BackgroundFile":"WarriorArms"},{"ID":41,"Name_enUS":"Fire","Name_enGB":"","Name_koKR":"","Name_frFR":"","Name_deDE":"","Name_enCN":"","Name_zhCN":"","Name_enTW":"","Name_Mask":4128894,"SpellIconID":11,"RaceMask":511,"ClassMask":128,"OrderIndex":0,"BackgroundFile":"MageFire"},{"ID":182,"Name_enUS":"Assassination","Name_enGB":"","Name_koKR":"","Name_frFR":"","Name_deDE":"","Name_enCN":"","Name_zhCN":"","Name_enTW":"","Name_Mask":4128894,"SpellIconID":498,"RaceMask":511,"ClassMask":8,"OrderIndex":0,"BackgroundFile":"RogueAssassination"},{"ID":81,"Name_enUS":"Arcane","Name_enGB":"","Name_koKR":"","Name_frFR":"","Name_deDE":"","Name_enCN":"","Name_zhCN":"","Name_enTW":"","Name_Mask":4128894,"SpellIconID":122,"RaceMask":511,"ClassMask":128,"OrderIndex":0,"BackgroundFile":"MageArcane"},{"ID":382,"Name_enUS":"Holy","Name_enGB":"","Name_koKR":"","Name_frFR":"","Name_deDE":"","Name_enCN":"","Name_zhCN":"","Name_enTW":"","Name_Mask":4128894,"SpellIconID":70,"RaceMask":511,"ClassMask":2,"OrderIndex":0,"BackgroundFile":"PaladinHoly"},{"ID":283,"Name_enUS":"Balance","Name_enGB":"","Name_koKR":"","Name_frFR":"","Name_deDE":"","Name_enCN":"","Name_zhCN":"","Name_enTW":"","Name_Mask":4128894,"SpellIconID":62,"RaceMask":511,"ClassMask":1024,"OrderIndex":0,"BackgroundFile":"DruidBalance"},{"ID":261,"Name_enUS":"Elemental","Name_enGB":"","Name_koKR":"","Name_frFR":"","Name_deDE":"","Name_enCN":"","Name_zhCN":"","Name_enTW":"","Name_Mask":4128894,"SpellIconID":1137,"RaceMask":511,"ClassMask":64,"OrderIndex":0,"BackgroundFile":"ShamanElementalCombat"},{"ID":282,"Name_enUS":"Restoration","Name_enGB":"","Name_koKR":"","Name_frFR":"","Name_deDE":"","Name_enCN":"","Name_zhCN":"","Name_enTW":"","Name_Mask":4128894,"SpellIconID":962,"RaceMask":511,"ClassMask":1024,"OrderIndex":2,"BackgroundFile":"DruidRestoration"},{"ID":301,"Name_enUS":"Destruction","Name_enGB":"","Name_koKR":"","Name_frFR":"","Name_deDE":"","Name_enCN":"","Name_zhCN":"","Name_enTW":"","Name_Mask":4128894,"SpellIconID":937,"RaceMask":511,"ClassMask":256,"OrderIndex":2,"BackgroundFile":"WarlockDestruction"},{"ID":183,"Name_enUS":"Subtlety","Name_enGB":"","Name_koKR":"","Name_frFR":"","Name_deDE":"","Name_enCN":"","Name_zhCN":"","Name_enTW":"","Name_Mask":4128894,"SpellIconID":103,"RaceMask":511,"ClassMask":8,"OrderIndex":2,"BackgroundFile":"RogueSubtlety"},{"ID":381,"Name_enUS":"Retribution","Name_enGB":"","Name_koKR":"","Name_frFR":"","Name_deDE":"","Name_enCN":"","Name_zhCN":"","Name_enTW":"","Name_Mask":4128894,"SpellIconID":555,"RaceMask":511,"ClassMask":2,"OrderIndex":2,"BackgroundFile":"PaladinCombat"},{"ID":262,"Name_enUS":"Restoration","Name_enGB":"","Name_koKR":"","Name_frFR":"","Name_deDE":"","Name_enCN":"","Name_zhCN":"","Name_enTW":"","Name_Mask":4128894,"SpellIconID":963,"RaceMask":511,"ClassMask":64,"OrderIndex":2,"BackgroundFile":"ShamanRestoration"},{"ID":163,"Name_enUS":"Protection","Name_enGB":"","Name_koKR":"","Name_frFR":"","Name_deDE":"","Name_enCN":"","Name_zhCN":"","Name_enTW":"","Name_Mask":4128894,"SpellIconID":1463,"RaceMask":511,"ClassMask":1,"OrderIndex":2,"BackgroundFile":"WarriorProtection"},{"ID":383,"Name_enUS":"Protection","Name_enGB":"","Name_koKR":"","Name_frFR":"","Name_deDE":"","Name_enCN":"","Name_zhCN":"","Name_enTW":"","Name_Mask":4128894,"SpellIconID":291,"RaceMask":511,"ClassMask":2,"OrderIndex":1,"BackgroundFile":"PaladinProtection"},{"ID":181,"Name_enUS":"Combat","Name_enGB":"","Name_koKR":"","Name_frFR":"","Name_deDE":"","Name_enCN":"","Name_zhCN":"","Name_enTW":"","Name_Mask":4128894,"SpellIconID":1501,"RaceMask":511,"ClassMask":8,"OrderIndex":1,"BackgroundFile":"RogueCombat"},{"ID":201,"Name_enUS":"Discipline","Name_enGB":"","Name_koKR":"","Name_frFR":"","Name_deDE":"","Name_enCN":"","Name_zhCN":"","Name_enTW":"","Name_Mask":4128894,"SpellIconID":555,"RaceMask":511,"ClassMask":16,"OrderIndex":0,"BackgroundFile":"PriestDiscipline"},{"ID":363,"Name_enUS":"Marksmanship","Name_enGB":"","Name_koKR":"","Name_frFR":"","Name_deDE":"","Name_enCN":"","Name_zhCN":"","Name_enTW":"","Name_Mask":4128894,"SpellIconID":126,"RaceMask":511,"ClassMask":4,"OrderIndex":1,"BackgroundFile":"HunterMarksmanship"}]